mnd_utils/__init__.py
mnd_utils/custom_typing.py
mnd_utils/drawing.py
mnd_utils/files.py
mnd_utils/image.py
mnd_utils/inspection.py
mnd_utils/misc.py
mnd_utils/rectangles.py
mnd_utils/video.py
mnd_utils/datastructures/__init__.py
mnd_utils/datastructures/circular_generator.py
mnd_utils/datastructures/dict_cache.py
mnd_utils/datastructures/stream.py
mnd_utils-0.1.8.dist-info/LICENSE
mnd_utils-0.1.8.dist-info/METADATA
mnd_utils-0.1.8.dist-info/WHEEL
mnd_utils-0.1.8.dist-info/top_level.txt
mnd_utils-0.1.8.dist-info/RECORD
