Metadata-Version: 2.1
Name: mnd-utils
Version: 0.1.8
Summary: Utility funtions and classes
Home-page: https://github.com/mnicolas94/python_utils
Author: Miguel Nicolás-Díaz
Author-email: miguelcok27@gmail.com
License: UNKNOWN
Platform: UNKNOWN
Classifier: Programming Language :: Python :: 3
Classifier: License :: OSI Approved :: MIT License
Classifier: Operating System :: OS Independent
Classifier: Development Status :: 3 - Alpha
Classifier: Intended Audience :: Developers
Requires-Python: >=3.6
License-File: LICENSE
Requires-Dist: numpy
Requires-Dist: opencv-python
Requires-Dist: pandas
Requires-Dist: requests
Requires-Dist: typing-extensions
